{
"type": "FeatureCollection",
"name": "all_candidates",
"crs": { "type": "name", "properties": { "name": "urn:ogc:def:crs:OGC:1.3:CRS84" } },
"features": [
{ "type": "Feature", "properties": { "address": "53 Waterford Avenue, Maribyrnong, Vic 3032", "ptv_walkable_5min": true, "ptv_walkable_15min": true, "ptv_walkability_colour": "#A67C00", "link": "https://www.realestate.com.au/property-house-vic-maribyrnong-428214586", "rent": 625.0, "bedrooms": 3.0, "bathrooms": 1.0, "parking": 2.0, "lat": -37.7724746, "lon": 144.8795149 }, "geometry": { "type": "Point", "coordinates": [ 144.8795149, -37.7724746 ] } },
{ "type": "Feature", "properties": { "address": "2A Kalang Rd, Glenroy, Vic 3046", "ptv_walkable_5min": false, "ptv_walkable_15min": true, "ptv_walkability_colour": "#00C864", "link": "https://www.realestate.com.au/property-townhouse-vic-glenroy-442440684", "rent": null, "bedrooms": null, "bathrooms": null, "parking": null, "lat": -37.7100322, "lon": 144.9220608 }, "geometry": { "type": "Point", "coordinates": [ 144.9220608, -37.7100322 ] } },
{ "type": "Feature", "properties": { "address": "1/4 Cochrane Ct, Essendon, Vic 3040", "ptv_walkable_5min": false, "ptv_walkable_15min": true, "ptv_walkability_colour": "#00C864", "link": "https://www.realestate.com.au/property-townhouse-vic-essendon-442596936", "rent": 680.0, "bedrooms": 3.0, "bathrooms": 1.0, "parking": 2.0, "lat": -37.7470524, "lon": 144.9277315 }, "geometry": { "type": "Point", "coordinates": [ 144.9277315, -37.7470524 ] } },
{ "type": "Feature", "properties": { "address": "8 Poble Walk, Avondale Heights, Vic 3034", "ptv_walkable_5min": false, "ptv_walkable_15min": false, "ptv_walkability_colour": "#800000", "link": null, "rent": null, "bedrooms": null, "bathrooms": null, "parking": null, "lat": -37.7641157, "lon": 144.8623721 }, "geometry": { "type": "Point", "coordinates": [ 144.862372099999988, -37.7641157 ] } }
]
}
